setup.cfg
setup.py
eubh.egg-info/PKG-INFO
eubh.egg-info/SOURCES.txt
eubh.egg-info/dependency_links.txt
eubh.egg-info/entry_points.txt
eubh.egg-info/requires.txt
eubh.egg-info/top_level.txt
eubh.egg-info/zip-safe
src/__init__.py
src/__main__.py
src/eubh/__init__.py
src/eubh/api.py
src/eubh/config.py
src/eubh/eubc_server_api.py
src/eubh/get.py
src/eubh/init.py
src/eubh/project.py
src/eubh/project_client.py
src/eubh/publish.py
src/eubh/put.py
src/eubh/status.py
src/eubh/user.py
src/eubh/utils.py
src/eubh/watch.py
src/eubh/chain/__init__.py
src/eubh/logs/__init__.py
src/eubh/logs/container_log.py
src/eubh/server/__init__.py
src/eubh/server/client_sse.py
src/eubh/server/sse.py
src/eubh/wesockets/__init__.py
src/eubh/wesockets/container_log.py
src/eubh/wesockets/on_sse_acceptor_event.py