Metadata-Version: 1.0
Name: eubh
Version: 0.1.2
Summary: eub client help
Home-page: UNKNOWN
Author: eubchain
Author-email: service@eubchain.com
License: UNKNOWN
Keywords: eub client help
Platform: UNKNOWN
